voiceit2/__init__.py
voiceit2/voiceit2.py
voiceit2-2.6.1.dist-info/LICENSE
voiceit2-2.6.1.dist-info/METADATA
voiceit2-2.6.1.dist-info/WHEEL
voiceit2-2.6.1.dist-info/top_level.txt
voiceit2-2.6.1.dist-info/RECORD
