Metadata-Version: 2.1
Name: voiceit2
Version: 2.6.1
Summary: VoiceIt API 2.0 Python Wrapper
Home-page: https://github.com/voiceittech/VoiceIt2-Python
Author: Hassan Ismaeel
Author-email: hassan@voiceit.io
License: UNKNOWN
Download-URL: https://github.com/voiceittech/VoiceIt2-Python/archive/2.6.1.tar.gz
Keywords: biometrics,voice verification,voice biometrics
Platform: UNKNOWN
Classifier: Programming Language :: Python :: 3
Classifier: License :: OSI Approved :: MIT License
Classifier: Operating System :: OS Independent
License-File: LICENSE
Requires-Dist: requests
